{
  "gender bender": [
    "genderbending",
    "gender bending",
    "gender bender",
    "magical sex shift"
  ],
  "all girls school": [
    "all-girls school"
  ],
  "boys love": [
    "boys' love",
    "bl"
  ],
  "anthropomorphic": [
    "anthropomorphism"
  ],
  "agender": [
    "asexual"
  ],
  "assassin": [
    "assassins"
  ],
  "butler": [
    "butlers"
  ],
  "card battle": [
    "card battles"
  ],
  "centaur": [
    "centaurs"
  ],
  "combat sport": [
    "combat sports"
  ],
  "cross dressing": [
    "crossdressing"
  ],
  "delinquent": [
    "delinquents"
  ],
  "detective": [
    "detectives"
  ],
  "disney": [
    "disney+ original"
  ],
  "elf": [
    "elve",
    "elves"
  ],
  "girls love": [
    "girls' love",
    "gl"
  ],
  "high stakes game": [
    "high stakes games",
    "high - stakes game",
    "high-stakes game"
  ],
  "idol": [
    "idols"
  ],
  "lgbt themes": [
    "lgbtq+ themes",
    "lgbtq + themes"
  ],
  "maid": [
    "maids"
  ],
  "mermaid": [
    "mermaids"
  ],
  "military": [
    "military, ",
    "military,",
    "millitary"
  ],
  "monster girl": [
    "monster girls"
  ],
  "nurse": [
    "nurses"
  ],
  "orphan": [
    "orphans"
  ],
  "politics": [
    "political"
  ],
  "real robot": [
    "real robots"
  ],
  "ship": [
    "ships"
  ],
  "shoujo ai": [
    "shoujo-ai",
    "shoujo - ai",
    "shoujo ai"
  ],
  "shounen ai": [
    "shounen-ai",
    "shounen - ai"
  ],
  "skeleton": [
    "skeletons"
  ],
  "stop motion": [
    "stop motion animation"
  ],
  "super robot": [
    "super robots"
  ],
  "superhero": [
    "superheroes"
  ],
  "superpower": [
    "superpowers"
  ],
  "teacher": [
    "teachers"
  ],
  "team sport": [
    "team sports"
  ],
  "vampire": [
    "vampires"
  ],
  "alien": [
    "aliens"
  ],
  "america": [
    "americas"
  ],
  "android": [
    "androids"
  ],
  "angel": [
    "angels"
  ],
  "avant garde": [
    "avant-garde"
  ],
  "bakumatsu - meiji period": [
    "bakumatsu meiji period"
  ],
  "biographie": [
    "biographical",
    "biographies"
  ],
  "bounty hunter": [
    "bounty hunters"
  ],
  "cyborg": [
    "cyborgs"
  ],
  "demon": [
    "demons"
  ],
  "dragon": [
    "dragons"
  ],
  "ghost": [
    "ghosts"
  ],
  "pirate": [
    "pirates"
  ],
  "post apocalypse": [
    "post-apocalyptic"
  ],
  "power suit": [
    "power suits"
  ],
  "pregnant": [
    "pregnancy"
  ],
  "psychic powers": [
    "psi-powers"
  ],
  "robot": [
    "robots"
  ],
  "sci-fi": [
    "sci fi"
  ],
  "science fiction": [
    "science-fiction"
  ],
  "thief": [
    "thieves"
  ],
  "werewolf": [
    "werewolves"
  ],
  "witch": [
    "witches"
  ],
  "work life": [
    "working life"
  ],
  "world war 2": [
    "world war ii"
  ],
  "zombie": [
    "zombies"
  ]
}